cplayer/__init__.py
cplayer/__main__.py
cplayer/documentation/help.md
cplayer/resources/config/default.yaml
cplayer/resources/styles/application.css
cplayer/src/__init__.py
cplayer/src/components/__init__.py
cplayer/src/components/file_explorer/__init__.py
cplayer/src/components/file_explorer/styles.css
cplayer/src/components/hidden_widget/__init__.py
cplayer/src/components/input_label/__init__.py
cplayer/src/components/input_label/styles.css
cplayer/src/components/notification/__init__.py
cplayer/src/components/notification/styles.css
cplayer/src/components/options_list/__init__.py
cplayer/src/components/options_list/styles.css
cplayer/src/components/progress_bar/__init__.py
cplayer/src/components/progress_bar/styles.css
cplayer/src/components/status_song/__init__.py
cplayer/src/components/status_song/styles.css
cplayer/src/components/tracklist/__init__.py
cplayer/src/components/tracklist/styles.css
cplayer/src/components/volume_bar/__init__.py
cplayer/src/components/volume_bar/styles.css
cplayer/src/elements/__init__.py
cplayer/src/elements/config.py
cplayer/src/elements/downloader.py
cplayer/src/elements/playlist.py
cplayer/src/pages/__init__.py
cplayer/src/pages/base/__init__.py
cplayer/src/pages/base/styles.css
cplayer/src/pages/help/__init__.py
cplayer/src/pages/help/styles.css
cplayer/src/pages/home/__init__.py
cplayer/src/pages/home/styles.css
cplayer-1.3.2.dist-info/LICENSE
cplayer-1.3.2.dist-info/METADATA
cplayer-1.3.2.dist-info/WHEEL
cplayer-1.3.2.dist-info/entry_points.txt
cplayer-1.3.2.dist-info/RECORD
