Metadata-Version: 2.1
Name: cplayer
Version: 1.3.2
Summary: Minimalist song player implemented with Python
Home-page: https://github.com/eccanto/cplayer
License: MIT
Keywords: music,songs player,command line
Author: Erik Ccanto
Author-email: ccanto.erik@gmail.com
Requires-Python: >=3.10,<4.0
Classifier: Development Status :: 4 - Beta
Classifier: Environment :: Console
Classifier: Intended Audience :: Developers
Classifier: License :: OSI Approved :: MIT License
Classifier: Operating System :: OS Independent
Classifier: Operating System :: Unix
Classifier: Programming Language :: Python
Classifier: Programming Language :: Python :: 3
Classifier: Programming Language :: Python :: 3.10
Classifier: Programming Language :: Python :: 3.11
Classifier: Programming Language :: Python :: 3.12
Requires-Dist: click (>=8.1.7,<9.0.0)
Requires-Dist: dotmap (>=1.3.30,<2.0.0)
Requires-Dist: numpy (>=1.26.4,<2.0.0)
Requires-Dist: pip (>=24.0,<25.0)
Requires-Dist: pydub (>=0.25.1,<0.26.0)
Requires-Dist: pygame (>=2.5.2,<3.0.0)
Requires-Dist: pyyaml (>=6.0.1,<7.0.0)
Requires-Dist: textual (>=0.58.0,<0.59.0)
Requires-Dist: tox (>=4.14.1,<5.0.0)
Requires-Dist: yt-dlp (>=2024.3.10,<2025.0.0)
Project-URL: Repository, https://github.com/eccanto/cplayer
